cubicweb_spacyquery/__init__.py
cubicweb_spacyquery/__pkginfo__.py
cubicweb_spacyquery/ccplugin.py
cubicweb_spacyquery/entities.py
cubicweb_spacyquery/hooks.py
cubicweb_spacyquery/query_extractor.py
cubicweb_spacyquery/schema.py
cubicweb_spacyquery/spacy_extractor.py
cubicweb_spacyquery/spacyquery.py
cubicweb_spacyquery/uiprops.py
cubicweb_spacyquery/views.py
cubicweb_spacyquery/i18n/de.po
cubicweb_spacyquery/i18n/en.po
cubicweb_spacyquery/i18n/es.po
cubicweb_spacyquery/i18n/fr.po
cubicweb_spacyquery/pviews/__init__.py
cubicweb_spacyquery-0.1.8.dist-info/METADATA
cubicweb_spacyquery-0.1.8.dist-info/WHEEL
cubicweb_spacyquery-0.1.8.dist-info/entry_points.txt
cubicweb_spacyquery-0.1.8.dist-info/top_level.txt
cubicweb_spacyquery-0.1.8.dist-info/RECORD
