Metadata-Version: 2.1
Name: cubicweb-spacyquery
Version: 0.1.8
Summary: Helpers for generating RQL query with spacy
Home-page: https://forge.extranet.logilab.fr/cubicweb/cubes/spacyquery
Author: LOGILAB S.A. (Paris, FRANCE)
Author-email: contact@logilab.fr
License: LGPL
Classifier: Environment :: Web Environment
Classifier: Framework :: CubicWeb
Classifier: Programming Language :: Python :: 3
Classifier: Programming Language :: JavaScript
Requires-Dist: cubicweb <5.0.0,>=4.9.1
Requires-Dist: cubicweb-web <2.0.0,>1.3.3
Requires-Dist: networkx <4.0.0,>=3.4.2
Requires-Dist: pandas <3.0.0,>=2.2.3
Requires-Dist: spacy <4.0.0,>=3.8.5
Requires-Dist: spacy-download <2.0.0,>=1.1.0
Requires-Dist: openai <2.0.0,>=1.75.0
